{
  "tools": [
    {
      "name": "load_csv_file",
      "description": "Load a CSV file into memory for visualization. Returns dataset info including columns, row count, and sample data. Accepts absolute file paths from Windows, WSL, or Linux.",
      "inputSchema": {
        "type": "object",
        "properties": {
          "file_path": {
            "type": "string",
            "description": "Absolute path to CSV file (Windows C:\\path, WSL /mnt/c/path, or Linux /path format)"
          },
          "delimiter": {
            "type": "string",
            "description": "CSV delimiter character",
            "default": ","
          },
          "encoding": {
            "type": "string",
            "description": "File encoding",
            "default": "utf-8"
          }
        },
        "required": ["file_path"]
      }
    },
    {
      "name": "load_excel_file",
      "description": "Load an Excel file into memory. If sheet_name is empty, loads the first sheet. Returns dataset info including columns, row count, and sample data.",
      "inputSchema": {
        "type": "object",
        "properties": {
          "file_path": {
            "type": "string",
            "description": "Absolute path to Excel file (.xlsx or .xls)"
          },
          "sheet_name": {
            "type": "string",
            "description": "Sheet name to load (optional - loads first sheet if empty)"
          }
        },
        "required": ["file_path"]
      }
    },
    {
      "name": "connect_sql_database",
      "description": "Connect to SQL database and execute query. Supports PostgreSQL, MySQL, SQL Server.",
      "inputSchema": {
        "type": "object",
        "properties": {
          "connection_string": {
            "type": "string",
            "description": "Database connection string (format: dialect://username:password@host:port/database)"
          },
          "query": {
            "type": "string",
            "description": "SQL query to execute"
          }
        },
        "required": ["connection_string", "query"]
      }
    },
    {
      "name": "connect_mongodb",
      "description": "Connect to MongoDB and fetch data. Query should be a JSON string representing MongoDB query filter.",
      "inputSchema": {
        "type": "object",
        "properties": {
          "connection_string": {
            "type": "string",
            "description": "MongoDB connection string (mongodb://...)"
          },
          "database": {
            "type": "string",
            "description": "Database name"
          },
          "collection": {
            "type": "string",
            "description": "Collection name"
          },
          "query": {
            "type": "string",
            "description": "MongoDB query filter as JSON string",
            "default": "{}"
          }
        },
        "required": ["connection_string", "database", "collection"]
      }
    },
    {
      "name": "load_aws_s3_file",
      "description": "Load a CSV or Excel file from AWS S3. Requires AWS credentials.",
      "inputSchema": {
        "type": "object",
        "properties": {
          "bucket_name": {
            "type": "string",
            "description": "S3 bucket name"
          },
          "file_key": {
            "type": "string",
            "description": "File key/path in bucket"
          },
          "aws_access_key": {
            "type": "string",
            "description": "AWS access key (optional if using default credentials)"
          },
          "aws_secret_key": {
            "type": "string",
            "description": "AWS secret key (optional if using default credentials)"
          },
          "region": {
            "type": "string",
            "description": "AWS region",
            "default": "us-east-1"
          }
        },
        "required": ["bucket_name", "file_key"]
      }
    },
    {
      "name": "load_gcp_bigquery",
      "description": "Load data from Google BigQuery.",
      "inputSchema": {
        "type": "object",
        "properties": {
          "project_id": {
            "type": "string",
            "description": "GCP project ID"
          },
          "query": {
            "type": "string",
            "description": "SQL query to execute against BigQuery"
          },
          "credentials_json": {
            "type": "string",
            "description": "Path to service account JSON file (optional if using default credentials)"
          }
        },
        "required": ["project_id", "query"]
      }
    },
    {
      "name": "load_azure_blob",
      "description": "Load a CSV or Excel file from Azure Blob Storage.",
      "inputSchema": {
        "type": "object",
        "properties": {
          "account_name": {
            "type": "string",
            "description": "Azure storage account name"
          },
          "container_name": {
            "type": "string",
            "description": "Container name"
          },
          "blob_name": {
            "type": "string",
            "description": "Blob file name"
          },
          "account_key": {
            "type": "string",
            "description": "Azure storage account key"
          }
        },
        "required": ["account_name", "container_name", "blob_name", "account_key"]
      }
    },
    {
      "name": "list_loaded_datasets",
      "description": "List all datasets currently loaded in memory with their IDs and basic information including row count and memory usage."
    },
    {
      "name": "preview_dataset",
      "description": "Preview a loaded dataset. Shows first N rows with column information and statistics.",
      "inputSchema": {
        "type": "object",
        "properties": {
          "dataset_id": {
            "type": "string",
            "description": "ID of the dataset to preview"
          },
          "num_rows": {
            "type": "string",
            "description": "Number of rows to preview",
            "default": "10"
          }
        },
        "required": ["dataset_id"]
      }
    },
    {
      "name": "create_bar_chart",
      "description": "Create an interactive bar chart using Plotly. Returns HTML file path.",
      "inputSchema": {
        "type": "object",
        "properties": {
          "dataset_id": {
            "type": "string",
            "description": "ID of loaded dataset"
          },
          "x_column": {
            "type": "string",
            "description": "Column name for X-axis"
          },
          "y_column": {
            "type": "string",
            "description": "Column name for Y-axis"
          },
          "title": {
            "type": "string",
            "description": "Chart title"
          },
          "output_path": {
            "type": "string",
            "description": "Path to save HTML output",
            "default": "/app/outputs/bar_chart.html"
          }
        },
        "required": ["dataset_id", "x_column", "y_column"]
      }
    },
    {
      "name": "create_line_chart",
      "description": "Create an interactive line chart using Plotly. Useful for time series data. Returns HTML file path.",
      "inputSchema": {
        "type": "object",
        "properties": {
          "dataset_id": {
            "type": "string",
            "description": "ID of loaded dataset"
          },
          "x_column": {
            "type": "string",
            "description": "Column name for X-axis"
          },
          "y_column": {
            "type": "string",
            "description": "Column name for Y-axis"
          },
          "title": {
            "type": "string",
            "description": "Chart title"
          },
          "output_path": {
            "type": "string",
            "description": "Path to save HTML output",
            "default": "/app/outputs/line_chart.html"
          }
        },
        "required": ["dataset_id", "x_column", "y_column"]
      }
    },
    {
      "name": "create_pie_chart",
      "description": "Create an interactive pie chart using Plotly. Returns HTML file path.",
      "inputSchema": {
        "type": "object",
        "properties": {
          "dataset_id": {
            "type": "string",
            "description": "ID of loaded dataset"
          },
          "names_column": {
            "type": "string",
            "description": "Column name for pie slice labels"
          },
          "values_column": {
            "type": "string",
            "description": "Column name for pie slice values"
          },
          "title": {
            "type": "string",
            "description": "Chart title"
          },
          "output_path": {
            "type": "string",
            "description": "Path to save HTML output",
            "default": "/app/outputs/pie_chart.html"
          }
        },
        "required": ["dataset_id", "names_column", "values_column"]
      }
    },
    {
      "name": "create_scatter_plot",
      "description": "Create an interactive scatter plot using Plotly. Optionally color points by a third column. Returns HTML file path.",
      "inputSchema": {
        "type": "object",
        "properties": {
          "dataset_id": {
            "type": "string",
            "description": "ID of loaded dataset"
          },
          "x_column": {
            "type": "string",
            "description": "Column name for X-axis"
          },
          "y_column": {
            "type": "string",
            "description": "Column name for Y-axis"
          },
          "color_column": {
            "type": "string",
            "description": "Optional column name for point colors"
          },
          "title": {
            "type": "string",
            "description": "Chart title"
          },
          "output_path": {
            "type": "string",
            "description": "Path to save HTML output",
            "default": "/app/outputs/scatter_plot.html"
          }
        },
        "required": ["dataset_id", "x_column", "y_column"]
      }
    },
    {
      "name": "create_heatmap",
      "description": "Create a correlation heatmap for numeric columns in the dataset using Plotly. Returns HTML file path.",
      "inputSchema": {
        "type": "object",
        "properties": {
          "dataset_id": {
            "type": "string",
            "description": "ID of loaded dataset"
          },
          "title": {
            "type": "string",
            "description": "Chart title",
            "default": "Correlation Heatmap"
          },
          "output_path": {
            "type": "string",
            "description": "Path to save HTML output",
            "default": "/app/outputs/heatmap.html"
          }
        },
        "required": ["dataset_id"]
      }
    },
    {
      "name": "create_histogram",
      "description": "Create an interactive histogram using Plotly. Returns HTML file path.",
      "inputSchema": {
        "type": "object",
        "properties": {
          "dataset_id": {
            "type": "string",
            "description": "ID of loaded dataset"
          },
          "column": {
            "type": "string",
            "description": "Column name for histogram"
          },
          "bins": {
            "type": "string",
            "description": "Number of bins",
            "default": "30"
          },
          "title": {
            "type": "string",
            "description": "Chart title"
          },
          "output_path": {
            "type": "string",
            "description": "Path to save HTML output",
            "default": "/app/outputs/histogram.html"
          }
        },
        "required": ["dataset_id", "column"]
      }
    },
    {
      "name": "create_box_plot",
      "description": "Create an interactive box plot using Plotly. If x_column is provided, creates grouped box plots. Returns HTML file path.",
      "inputSchema": {
        "type": "object",
        "properties": {
          "dataset_id": {
            "type": "string",
            "description": "ID of loaded dataset"
          },
          "y_column": {
            "type": "string",
            "description": "Column name for Y-axis"
          },
          "x_column": {
            "type": "string",
            "description": "Optional column name for grouping"
          },
          "title": {
            "type": "string",
            "description": "Chart title"
          },
          "output_path": {
            "type": "string",
            "description": "Path to save HTML output",
            "default": "/app/outputs/box_plot.html"
          }
        },
        "required": ["dataset_id", "y_column"]
      }
    },
    {
      "name": "create_dashboard",
      "description": "Create a comprehensive dashboard with multiple visualizations for the dataset. Returns HTML file path.",
      "inputSchema": {
        "type": "object",
        "properties": {
          "dataset_id": {
            "type": "string",
            "description": "ID of loaded dataset"
          },
          "title": {
            "type": "string",
            "description": "Dashboard title",
            "default": "Interactive Dashboard"
          },
          "output_path": {
            "type": "string",
            "description": "Path to save HTML output",
            "default": "/app/outputs/dashboard.html"
          }
        },
        "required": ["dataset_id"]
      }
    },
    {
      "name": "generate_summary_report",
      "description": "Generate a comprehensive statistical summary report of the dataset including missing values, data types, and basic statistics."
    },
    {
      "name": "get_file_path_help",
      "description": "Get instructions on how to provide file paths to the DataViz server when using Cursor or other MCP clients. Returns information about supported path formats and configuration methods."
    }
  ]
}
